{
  "uid": "11012909",
  "pubdate": "2000 Oct",
  "epubdate": "",
  "source": "Kidney Int",
  "authors": [
    {
      "name": "Barenbrock M",
      "authtype": "Author",
      "clusterid": ""
    },
    {
      "name": "Hausberg M",
      "authtype": "Author",
      "clusterid": ""
    },
    {
      "name": "Matzkies F",
      "authtype": "Author",
      "clusterid": ""
    },
    {
      "name": "de la Motte S",
      "authtype": "Author",
      "clusterid": ""
    },
    {
      "name": "Schaefer RM",
      "authtype": "Author",
      "clusterid": ""
    }
  ],
  "lastauthor": "Schaefer RM",
  "title": "Effects of bicarbonate- and lactate-buffered replacement fluids on cardiovascular outcome in CVVH patients.",
  "sorttitle": "effects of bicarbonate and lactate buffered replacement fluids on cardiovascular outcome in cvvh patients",
  "volume": "58",
  "issue": "4",
  "pages": "1751-7",
  "lang": [
    "eng"
  ],
  "nlmuniqueid": "0323470",
  "issn": "0085-2538",
  "essn": "1523-1755",
  "pubtype": [
    "Clinical Trial",
    "Journal Article",
    "Multicenter Study",
    "Randomized Controlled Trial"
  ],
  "recordstatus": "PubMed - indexed for MEDLINE",
  "pubstatus": "4",
  "articleids": [
    {
      "idtype": "pubmed",
      "idtypen": 1,
      "value": "11012909"
    },
    {
      "idtype": "pii",
      "idtypen": 4,
      "value": "S0085-2538(15)47273-4"
    },
    {
      "idtype": "doi",
      "idtypen": 3,
      "value": "10.1046/j.1523-1755.2000.00336.x"
    },
    {
      "idtype": "rid",
      "idtypen": 8,
      "value": "11012909"
    },
    {
      "idtype": "eid",
      "idtypen": 8,
      "value": "11012909"
    }
  ],
  "history": [
    {
      "pubstatus": "pubmed",
      "date": "2000/09/30 11:00"
    },
    {
      "pubstatus": "medline",
      "date": "2001/02/28 10:01"
    },
    {
      "pubstatus": "entrez",
      "date": "2000/09/30 11:00"
    }
  ],
  "references": [],
  "attributes": [
    "Has Abstract"
  ],
  "pmcrefcount": 11,
  "fulljournalname": "Kidney international",
  "elocationid": "",
  "doctype": "citation",
  "srccontriblist": [],
  "booktitle": "",
  "medium": "",
  "edition": "",
  "publisherlocation": "",
  "publishername": "",
  "srcdate": "",
  "reportnumber": "",
  "availablefromurl": "",
  "locationlabel": "",
  "doccontriblist": [],
  "docdate": "",
  "bookname": "",
  "chapter": "",
  "sortpubdate": "2000/10/01 00:00",
  "sortfirstauthor": "Barenbrock M",
  "vernaculartitle": ""
}