{
  "uid": "15121724",
  "pubdate": "2004 Jun",
  "epubdate": "2004 Apr 30",
  "source": "Br J Anaesth",
  "authors": [
    {
      "name": "Walsh TS",
      "authtype": "Author",
      "clusterid": ""
    },
    {
      "name": "Dodds S",
      "authtype": "Author",
      "clusterid": ""
    },
    {
      "name": "McArdle F",
      "authtype": "Author",
      "clusterid": ""
    }
  ],
  "lastauthor": "McArdle F",
  "title": "Evaluation of simple criteria to predict successful weaning from mechanical ventilation in intensive care patients.",
  "sorttitle": "evaluation of simple criteria to predict successful weaning from mechanical ventilation in intensive care patients",
  "volume": "92",
  "issue": "6",
  "pages": "793-9",
  "lang": [
    "eng"
  ],
  "nlmuniqueid": "0372541",
  "issn": "0007-0912",
  "essn": "1471-6771",
  "pubtype": [
    "Journal Article"
  ],
  "recordstatus": "PubMed - indexed for MEDLINE",
  "pubstatus": "256",
  "articleids": [
    {
      "idtype": "pubmed",
      "idtypen": 1,
      "value": "15121724"
    },
    {
      "idtype": "doi",
      "idtypen": 3,
      "value": "10.1093/bja/aeh139"
    },
    {
      "idtype": "pii",
      "idtypen": 4,
      "value": "S0007-0912(17)35552-6"
    },
    {
      "idtype": "rid",
      "idtypen": 8,
      "value": "15121724"
    },
    {
      "idtype": "eid",
      "idtypen": 8,
      "value": "15121724"
    }
  ],
  "history": [
    {
      "pubstatus": "pubmed",
      "date": "2004/05/04 05:00"
    },
    {
      "pubstatus": "medline",
      "date": "2004/06/24 05:00"
    },
    {
      "pubstatus": "entrez",
      "date": "2004/05/04 05:00"
    }
  ],
  "references": [],
  "attributes": [
    "Has Abstract"
  ],
  "pmcrefcount": 12,
  "fulljournalname": "British journal of anaesthesia",
  "elocationid": "",
  "doctype": "citation",
  "srccontriblist": [],
  "booktitle": "",
  "medium": "",
  "edition": "",
  "publisherlocation": "",
  "publishername": "",
  "srcdate": "",
  "reportnumber": "",
  "availablefromurl": "",
  "locationlabel": "",
  "doccontriblist": [],
  "docdate": "",
  "bookname": "",
  "chapter": "",
  "sortpubdate": "2004/06/01 00:00",
  "sortfirstauthor": "Walsh TS",
  "vernaculartitle": ""
}