{
  "uid": "16010769",
  "pubdate": "2005 Jun",
  "epubdate": "",
  "source": "AANA J",
  "authors": [
    {
      "name": "Williams JR",
      "authtype": "Author",
      "clusterid": ""
    }
  ],
  "lastauthor": "Williams JR",
  "title": "Anesthesia information management systems.",
  "sorttitle": "anesthesia information management systems",
  "volume": "73",
  "issue": "3",
  "pages": "178-81",
  "lang": [
    "eng"
  ],
  "nlmuniqueid": "0431420",
  "issn": "0094-6354",
  "essn": "2162-5239",
  "pubtype": [
    "Journal Article",
    "Review"
  ],
  "recordstatus": "PubMed - indexed for MEDLINE",
  "pubstatus": "4",
  "articleids": [
    {
      "idtype": "pubmed",
      "idtypen": 1,
      "value": "16010769"
    },
    {
      "idtype": "rid",
      "idtypen": 8,
      "value": "16010769"
    },
    {
      "idtype": "eid",
      "idtypen": 8,
      "value": "16010769"
    }
  ],
  "history": [
    {
      "pubstatus": "pubmed",
      "date": "2005/07/14 09:00"
    },
    {
      "pubstatus": "medline",
      "date": "2005/08/19 09:00"
    },
    {
      "pubstatus": "entrez",
      "date": "2005/07/14 09:00"
    }
  ],
  "references": [],
  "attributes": [
    "Has Abstract"
  ],
  "pmcrefcount": 1,
  "fulljournalname": "AANA journal",
  "elocationid": "",
  "doctype": "citation",
  "srccontriblist": [],
  "booktitle": "",
  "medium": "",
  "edition": "",
  "publisherlocation": "",
  "publishername": "",
  "srcdate": "",
  "reportnumber": "",
  "availablefromurl": "",
  "locationlabel": "",
  "doccontriblist": [],
  "docdate": "",
  "bookname": "",
  "chapter": "",
  "sortpubdate": "2005/06/01 00:00",
  "sortfirstauthor": "Williams JR",
  "vernaculartitle": ""
}