{
  "uid": "17938292",
  "pubdate": "2007 Oct 16",
  "epubdate": "",
  "source": "Circulation",
  "authors": [
    {
      "name": "Riddell JW",
      "authtype": "Author",
      "clusterid": ""
    },
    {
      "name": "Chiche L",
      "authtype": "Author",
      "clusterid": ""
    },
    {
      "name": "Plaud B",
      "authtype": "Author",
      "clusterid": ""
    },
    {
      "name": "Hamon M",
      "authtype": "Author",
      "clusterid": ""
    }
  ],
  "lastauthor": "Hamon M",
  "title": "Coronary stents and noncardiac surgery.",
  "sorttitle": "coronary stents and noncardiac surgery",
  "volume": "116",
  "issue": "16",
  "pages": "e378-82",
  "lang": [
    "eng"
  ],
  "nlmuniqueid": "0147763",
  "issn": "0009-7322",
  "essn": "1524-4539",
  "pubtype": [
    "Journal Article",
    "Review"
  ],
  "recordstatus": "PubMed - indexed for MEDLINE",
  "pubstatus": "4",
  "articleids": [
    {
      "idtype": "pubmed",
      "idtypen": 1,
      "value": "17938292"
    },
    {
      "idtype": "pii",
      "idtypen": 4,
      "value": "116/16/e378"
    },
    {
      "idtype": "doi",
      "idtypen": 3,
      "value": "10.1161/CIRCULATIONAHA.107.726992"
    },
    {
      "idtype": "rid",
      "idtypen": 8,
      "value": "17938292"
    },
    {
      "idtype": "eid",
      "idtypen": 8,
      "value": "17938292"
    }
  ],
  "history": [
    {
      "pubstatus": "pubmed",
      "date": "2007/10/17 09:00"
    },
    {
      "pubstatus": "medline",
      "date": "2007/12/11 09:00"
    },
    {
      "pubstatus": "entrez",
      "date": "2007/10/17 09:00"
    }
  ],
  "references": [],
  "attributes": [],
  "pmcrefcount": 3,
  "fulljournalname": "Circulation",
  "elocationid": "",
  "doctype": "citation",
  "srccontriblist": [],
  "booktitle": "",
  "medium": "",
  "edition": "",
  "publisherlocation": "",
  "publishername": "",
  "srcdate": "",
  "reportnumber": "",
  "availablefromurl": "",
  "locationlabel": "",
  "doccontriblist": [],
  "docdate": "",
  "bookname": "",
  "chapter": "",
  "sortpubdate": "2007/10/16 00:00",
  "sortfirstauthor": "Riddell JW",
  "vernaculartitle": ""
}