{
  "uid": "19194153",
  "pubdate": "2009 Feb",
  "epubdate": "",
  "source": "Anesthesiology",
  "authors": [
    {
      "name": "Timmermann A",
      "authtype": "Author",
      "clusterid": ""
    },
    {
      "name": "Cremer S",
      "authtype": "Author",
      "clusterid": ""
    },
    {
      "name": "Eich C",
      "authtype": "Author",
      "clusterid": ""
    },
    {
      "name": "Kazmaier S",
      "authtype": "Author",
      "clusterid": ""
    },
    {
      "name": "Bräuer A",
      "authtype": "Author",
      "clusterid": ""
    },
    {
      "name": "Graf BM",
      "authtype": "Author",
      "clusterid": ""
    },
    {
      "name": "Russo SG",
      "authtype": "Author",
      "clusterid": ""
    }
  ],
  "lastauthor": "Russo SG",
  "title": "Prospective clinical and fiberoptic evaluation of the Supreme laryngeal mask airway.",
  "sorttitle": "prospective clinical and fiberoptic evaluation of the supreme laryngeal mask airway",
  "volume": "110",
  "issue": "2",
  "pages": "262-5",
  "lang": [
    "eng"
  ],
  "nlmuniqueid": "1300217",
  "issn": "0003-3022",
  "essn": "1528-1175",
  "pubtype": [
    "Journal Article"
  ],
  "recordstatus": "PubMed - indexed for MEDLINE",
  "pubstatus": "4",
  "articleids": [
    {
      "idtype": "pubmed",
      "idtypen": 1,
      "value": "19194153"
    },
    {
      "idtype": "doi",
      "idtypen": 3,
      "value": "10.1097/ALN.0b013e3181942c4d"
    },
    {
      "idtype": "pii",
      "idtypen": 4,
      "value": "00000542-200902000-00014"
    },
    {
      "idtype": "rid",
      "idtypen": 8,
      "value": "19194153"
    },
    {
      "idtype": "eid",
      "idtypen": 8,
      "value": "19194153"
    }
  ],
  "history": [
    {
      "pubstatus": "entrez",
      "date": "2009/02/06 09:00"
    },
    {
      "pubstatus": "pubmed",
      "date": "2009/02/06 09:00"
    },
    {
      "pubstatus": "medline",
      "date": "2009/03/06 09:00"
    }
  ],
  "references": [],
  "attributes": [
    "Has Abstract"
  ],
  "pmcrefcount": 15,
  "fulljournalname": "Anesthesiology",
  "elocationid": "doi: 10.1097/ALN.0b013e3181942c4d",
  "doctype": "citation",
  "srccontriblist": [],
  "booktitle": "",
  "medium": "",
  "edition": "",
  "publisherlocation": "",
  "publishername": "",
  "srcdate": "",
  "reportnumber": "",
  "availablefromurl": "",
  "locationlabel": "",
  "doccontriblist": [],
  "docdate": "",
  "bookname": "",
  "chapter": "",
  "sortpubdate": "2009/02/01 00:00",
  "sortfirstauthor": "Timmermann A",
  "vernaculartitle": ""
}