{
  "uid": "21398304",
  "pubdate": "2011 Apr",
  "epubdate": "",
  "source": "J Antimicrob Chemother",
  "authors": [
    {
      "name": "McKenzie C",
      "authtype": "Author",
      "clusterid": ""
    }
  ],
  "lastauthor": "McKenzie C",
  "title": "Antibiotic dosing in critical illness.",
  "sorttitle": "antibiotic dosing in critical illness",
  "volume": "66 Suppl 2",
  "issue": "",
  "pages": "ii25-31",
  "lang": [
    "eng"
  ],
  "nlmuniqueid": "7513617",
  "issn": "0305-7453",
  "essn": "1460-2091",
  "pubtype": [
    "Journal Article",
    "Review"
  ],
  "recordstatus": "PubMed - indexed for MEDLINE",
  "pubstatus": "4",
  "articleids": [
    {
      "idtype": "pubmed",
      "idtypen": 1,
      "value": "21398304"
    },
    {
      "idtype": "pii",
      "idtypen": 4,
      "value": "dkq516"
    },
    {
      "idtype": "doi",
      "idtypen": 3,
      "value": "10.1093/jac/dkq516"
    },
    {
      "idtype": "rid",
      "idtypen": 8,
      "value": "21398304"
    },
    {
      "idtype": "eid",
      "idtypen": 8,
      "value": "21398304"
    }
  ],
  "history": [
    {
      "pubstatus": "entrez",
      "date": "2011/03/15 06:00"
    },
    {
      "pubstatus": "pubmed",
      "date": "2011/03/16 06:00"
    },
    {
      "pubstatus": "medline",
      "date": "2011/05/19 06:00"
    }
  ],
  "references": [],
  "attributes": [
    "Has Abstract"
  ],
  "pmcrefcount": 30,
  "fulljournalname": "The Journal of antimicrobial chemotherapy",
  "elocationid": "doi: 10.1093/jac/dkq516",
  "doctype": "citation",
  "srccontriblist": [],
  "booktitle": "",
  "medium": "",
  "edition": "",
  "publisherlocation": "",
  "publishername": "",
  "srcdate": "",
  "reportnumber": "",
  "availablefromurl": "",
  "locationlabel": "",
  "doccontriblist": [],
  "docdate": "",
  "bookname": "",
  "chapter": "",
  "sortpubdate": "2011/04/01 00:00",
  "sortfirstauthor": "McKenzie C",
  "vernaculartitle": ""
}