{
  "uid": "22156272",
  "pubdate": "2011 Dec",
  "epubdate": "",
  "source": "Br J Anaesth",
  "authors": [
    {
      "name": "Reitman E",
      "authtype": "Author",
      "clusterid": ""
    },
    {
      "name": "Flood P",
      "authtype": "Author",
      "clusterid": ""
    }
  ],
  "lastauthor": "Flood P",
  "title": "Anaesthetic considerations for non-obstetric surgery during pregnancy.",
  "sorttitle": "anaesthetic considerations for non obstetric surgery during pregnancy",
  "volume": "107 Suppl 1",
  "issue": "",
  "pages": "i72-8",
  "lang": [
    "eng"
  ],
  "nlmuniqueid": "0372541",
  "issn": "0007-0912",
  "essn": "1471-6771",
  "pubtype": [
    "Journal Article",
    "Review"
  ],
  "recordstatus": "PubMed - indexed for MEDLINE",
  "pubstatus": "4",
  "articleids": [
    {
      "idtype": "pubmed",
      "idtypen": 1,
      "value": "22156272"
    },
    {
      "idtype": "pii",
      "idtypen": 4,
      "value": "S0007-0912(17)32556-4"
    },
    {
      "idtype": "doi",
      "idtypen": 3,
      "value": "10.1093/bja/aer343"
    },
    {
      "idtype": "rid",
      "idtypen": 8,
      "value": "22156272"
    },
    {
      "idtype": "eid",
      "idtypen": 8,
      "value": "22156272"
    }
  ],
  "history": [
    {
      "pubstatus": "entrez",
      "date": "2011/12/14 06:00"
    },
    {
      "pubstatus": "pubmed",
      "date": "2011/12/22 06:00"
    },
    {
      "pubstatus": "medline",
      "date": "2012/02/02 06:00"
    }
  ],
  "references": [],
  "attributes": [
    "Has Abstract"
  ],
  "pmcrefcount": 32,
  "fulljournalname": "British journal of anaesthesia",
  "elocationid": "doi: 10.1093/bja/aer343",
  "doctype": "citation",
  "srccontriblist": [],
  "booktitle": "",
  "medium": "",
  "edition": "",
  "publisherlocation": "",
  "publishername": "",
  "srcdate": "",
  "reportnumber": "",
  "availablefromurl": "",
  "locationlabel": "",
  "doccontriblist": [],
  "docdate": "",
  "bookname": "",
  "chapter": "",
  "sortpubdate": "2011/12/01 00:00",
  "sortfirstauthor": "Reitman E",
  "vernaculartitle": ""
}