{
  "uid": "31826341",
  "pubdate": "2019 Dec 12",
  "epubdate": "",
  "source": "N Engl J Med",
  "authors": [
    {
      "name": "Castells M",
      "authtype": "Author",
      "clusterid": ""
    },
    {
      "name": "Khan DA",
      "authtype": "Author",
      "clusterid": ""
    },
    {
      "name": "Phillips EJ",
      "authtype": "Author",
      "clusterid": ""
    }
  ],
  "lastauthor": "Phillips EJ",
  "title": "Penicillin Allergy.",
  "sorttitle": "penicillin allergy",
  "volume": "381",
  "issue": "24",
  "pages": "2338-2351",
  "lang": [
    "eng"
  ],
  "nlmuniqueid": "0255562",
  "issn": "0028-4793",
  "essn": "1533-4406",
  "pubtype": [
    "Journal Article",
    "Review"
  ],
  "recordstatus": "PubMed - indexed for MEDLINE",
  "pubstatus": "4",
  "articleids": [
    {
      "idtype": "pubmed",
      "idtypen": 1,
      "value": "31826341"
    },
    {
      "idtype": "doi",
      "idtypen": 3,
      "value": "10.1056/NEJMra1807761"
    },
    {
      "idtype": "rid",
      "idtypen": 8,
      "value": "31826341"
    },
    {
      "idtype": "eid",
      "idtypen": 8,
      "value": "31826341"
    }
  ],
  "history": [
    {
      "pubstatus": "entrez",
      "date": "2019/12/12 06:00"
    },
    {
      "pubstatus": "pubmed",
      "date": "2019/12/12 06:00"
    },
    {
      "pubstatus": "medline",
      "date": "2020/01/03 06:00"
    }
  ],
  "references": [
    {
      "refsource": "N Engl J Med. 2020 Apr 2;382(14):1379",
      "reftype": "Comment in",
      "pmid": 32242377,
      "note": ""
    },
    {
      "refsource": "N Engl J Med. 2020 Apr 2;382(14):1379-1380",
      "reftype": "Comment in",
      "pmid": 32242378,
      "note": ""
    }
  ],
  "attributes": [],
  "pmcrefcount": 15,
  "fulljournalname": "The New England journal of medicine",
  "elocationid": "doi: 10.1056/NEJMra1807761",
  "doctype": "citation",
  "srccontriblist": [],
  "booktitle": "",
  "medium": "",
  "edition": "",
  "publisherlocation": "",
  "publishername": "",
  "srcdate": "",
  "reportnumber": "",
  "availablefromurl": "",
  "locationlabel": "",
  "doccontriblist": [],
  "docdate": "",
  "bookname": "",
  "chapter": "",
  "sortpubdate": "2019/12/12 00:00",
  "sortfirstauthor": "Castells M",
  "vernaculartitle": ""
}