{
  "uid": "33186158",
  "pubdate": "2020 Dec",
  "epubdate": "",
  "source": "Anesth Analg",
  "authors": [
    {
      "name": "Margraf A",
      "authtype": "Author",
      "clusterid": ""
    },
    {
      "name": "Ludwig N",
      "authtype": "Author",
      "clusterid": ""
    },
    {
      "name": "Zarbock A",
      "authtype": "Author",
      "clusterid": ""
    },
    {
      "name": "Rossaint J",
      "authtype": "Author",
      "clusterid": ""
    }
  ],
  "lastauthor": "Rossaint J",
  "title": "Systemic Inflammatory Response Syndrome After Surgery: Mechanisms and Protection.",
  "sorttitle": "systemic inflammatory response syndrome after surgery mechanisms and protection",
  "volume": "131",
  "issue": "6",
  "pages": "1693-1707",
  "lang": [
    "eng"
  ],
  "nlmuniqueid": "1310650",
  "issn": "0003-2999",
  "essn": "1526-7598",
  "pubtype": [
    "Journal Article",
    "Review"
  ],
  "recordstatus": "PubMed - indexed for MEDLINE",
  "pubstatus": "4",
  "articleids": [
    {
      "idtype": "pubmed",
      "idtypen": 1,
      "value": "33186158"
    },
    {
      "idtype": "doi",
      "idtypen": 3,
      "value": "10.1213/ANE.0000000000005175"
    },
    {
      "idtype": "pii",
      "idtypen": 4,
      "value": "00000539-202012000-00007"
    },
    {
      "idtype": "rid",
      "idtypen": 8,
      "value": "33186158"
    },
    {
      "idtype": "eid",
      "idtypen": 8,
      "value": "33186158"
    }
  ],
  "history": [
    {
      "pubstatus": "entrez",
      "date": "2020/11/13 17:08"
    },
    {
      "pubstatus": "pubmed",
      "date": "2020/11/14 06:00"
    },
    {
      "pubstatus": "medline",
      "date": "2020/12/22 06:00"
    }
  ],
  "references": [
    {
      "refsource": "Anesth Analg. 2020 Dec;131(6):1663-1665",
      "reftype": "Comment in",
      "pmid": 33186154,
      "note": ""
    }
  ],
  "attributes": [
    "Has Abstract"
  ],
  "pmcrefcount": "",
  "fulljournalname": "Anesthesia and analgesia",
  "elocationid": "doi: 10.1213/ANE.0000000000005175",
  "doctype": "citation",
  "srccontriblist": [],
  "booktitle": "",
  "medium": "",
  "edition": "",
  "publisherlocation": "",
  "publishername": "",
  "srcdate": "",
  "reportnumber": "",
  "availablefromurl": "",
  "locationlabel": "",
  "doccontriblist": [],
  "docdate": "",
  "bookname": "",
  "chapter": "",
  "sortpubdate": "2020/12/01 00:00",
  "sortfirstauthor": "Margraf A",
  "vernaculartitle": ""
}