{
  "uid": "3819792",
  "pubdate": "1987 Jan",
  "epubdate": "",
  "source": "J Clin Monit",
  "authors": [
    {
      "name": "Denisco RA",
      "authtype": "Author",
      "clusterid": ""
    },
    {
      "name": "Drummond JN",
      "authtype": "Author",
      "clusterid": ""
    },
    {
      "name": "Gravenstein JS",
      "authtype": "Author",
      "clusterid": ""
    }
  ],
  "lastauthor": "Gravenstein JS",
  "title": "The effect of fatigue on the performance of a simulated anesthetic monitoring task.",
  "sorttitle": "effect of fatigue on the performance of a simulated anesthetic monitoring task",
  "volume": "3",
  "issue": "1",
  "pages": "22-4",
  "lang": [
    "eng"
  ],
  "nlmuniqueid": "8506707",
  "issn": "0748-1977",
  "essn": "",
  "pubtype": [
    "Journal Article"
  ],
  "recordstatus": "PubMed - indexed for MEDLINE",
  "pubstatus": "4",
  "articleids": [
    {
      "idtype": "pubmed",
      "idtypen": 1,
      "value": "3819792"
    },
    {
      "idtype": "doi",
      "idtypen": 3,
      "value": "10.1007/BF00770879"
    },
    {
      "idtype": "rid",
      "idtypen": 8,
      "value": "3819792"
    },
    {
      "idtype": "eid",
      "idtypen": 8,
      "value": "3819792"
    }
  ],
  "history": [
    {
      "pubstatus": "pubmed",
      "date": "1987/01/01 00:00"
    },
    {
      "pubstatus": "medline",
      "date": "1987/01/01 00:01"
    },
    {
      "pubstatus": "entrez",
      "date": "1987/01/01 00:00"
    }
  ],
  "references": [],
  "attributes": [
    "Has Abstract"
  ],
  "pmcrefcount": 4,
  "fulljournalname": "Journal of clinical monitoring",
  "elocationid": "",
  "doctype": "citation",
  "srccontriblist": [],
  "booktitle": "",
  "medium": "",
  "edition": "",
  "publisherlocation": "",
  "publishername": "",
  "srcdate": "",
  "reportnumber": "",
  "availablefromurl": "",
  "locationlabel": "",
  "doccontriblist": [],
  "docdate": "",
  "bookname": "",
  "chapter": "",
  "sortpubdate": "1987/01/01 00:00",
  "sortfirstauthor": "Denisco RA",
  "vernaculartitle": ""
}