{
  "uid": "3840382",
  "pubdate": "1985 Nov",
  "epubdate": "",
  "source": "Br J Anaesth",
  "authors": [
    {
      "name": "Stiller RL",
      "authtype": "Author",
      "clusterid": ""
    },
    {
      "name": "Cook DR",
      "authtype": "Author",
      "clusterid": ""
    },
    {
      "name": "Chakravorti S",
      "authtype": "Author",
      "clusterid": ""
    }
  ],
  "lastauthor": "Chakravorti S",
  "title": "In vitro degradation of atracurium in human plasma.",
  "sorttitle": "in vitro degradation of atracurium in human plasma",
  "volume": "57",
  "issue": "11",
  "pages": "1085-8",
  "lang": [
    "eng"
  ],
  "nlmuniqueid": "0372541",
  "issn": "0007-0912",
  "essn": "1471-6771",
  "pubtype": [
    "Journal Article"
  ],
  "recordstatus": "PubMed - indexed for MEDLINE",
  "pubstatus": "4",
  "articleids": [
    {
      "idtype": "pubmed",
      "idtypen": 1,
      "value": "3840382"
    },
    {
      "idtype": "pii",
      "idtypen": 4,
      "value": "S0007-0912(17)41243-8"
    },
    {
      "idtype": "doi",
      "idtypen": 3,
      "value": "10.1093/bja/57.11.1085"
    },
    {
      "idtype": "rid",
      "idtypen": 8,
      "value": "3840382"
    },
    {
      "idtype": "eid",
      "idtypen": 8,
      "value": "3840382"
    }
  ],
  "history": [
    {
      "pubstatus": "pubmed",
      "date": "1985/11/01 00:00"
    },
    {
      "pubstatus": "medline",
      "date": "1985/11/01 00:01"
    },
    {
      "pubstatus": "entrez",
      "date": "1985/11/01 00:00"
    }
  ],
  "references": [],
  "attributes": [
    "Has Abstract"
  ],
  "pmcrefcount": "",
  "fulljournalname": "British journal of anaesthesia",
  "elocationid": "",
  "doctype": "citation",
  "srccontriblist": [],
  "booktitle": "",
  "medium": "",
  "edition": "",
  "publisherlocation": "",
  "publishername": "",
  "srcdate": "",
  "reportnumber": "",
  "availablefromurl": "",
  "locationlabel": "",
  "doccontriblist": [],
  "docdate": "",
  "bookname": "",
  "chapter": "",
  "sortpubdate": "1985/11/01 00:00",
  "sortfirstauthor": "Stiller RL",
  "vernaculartitle": ""
}