{
  "uid": "3893223",
  "pubdate": "1985 Aug",
  "epubdate": "",
  "source": "Anesth Analg",
  "authors": [
    {
      "name": "Benumof JL",
      "authtype": "Author",
      "clusterid": ""
    }
  ],
  "lastauthor": "Benumof JL",
  "title": "One-lung ventilation and hypoxic pulmonary vasoconstriction: implications for anesthetic management.",
  "sorttitle": "one lung ventilation and hypoxic pulmonary vasoconstriction implications for anesthetic management",
  "volume": "64",
  "issue": "8",
  "pages": "821-33",
  "lang": [
    "eng"
  ],
  "nlmuniqueid": "1310650",
  "issn": "0003-2999",
  "essn": "1526-7598",
  "pubtype": [
    "Journal Article",
    "Review"
  ],
  "recordstatus": "PubMed - indexed for MEDLINE",
  "pubstatus": "4",
  "articleids": [
    {
      "idtype": "pubmed",
      "idtypen": 1,
      "value": "3893223"
    },
    {
      "idtype": "rid",
      "idtypen": 8,
      "value": "3893223"
    },
    {
      "idtype": "eid",
      "idtypen": 8,
      "value": "3893223"
    }
  ],
  "history": [
    {
      "pubstatus": "pubmed",
      "date": "1985/08/01 00:00"
    },
    {
      "pubstatus": "medline",
      "date": "1985/08/01 00:01"
    },
    {
      "pubstatus": "entrez",
      "date": "1985/08/01 00:00"
    }
  ],
  "references": [],
  "attributes": [],
  "pmcrefcount": 18,
  "fulljournalname": "Anesthesia and analgesia",
  "elocationid": "",
  "doctype": "citation",
  "srccontriblist": [],
  "booktitle": "",
  "medium": "",
  "edition": "",
  "publisherlocation": "",
  "publishername": "",
  "srcdate": "",
  "reportnumber": "",
  "availablefromurl": "",
  "locationlabel": "",
  "doccontriblist": [],
  "docdate": "",
  "bookname": "",
  "chapter": "",
  "sortpubdate": "1985/08/01 00:00",
  "sortfirstauthor": "Benumof JL",
  "vernaculartitle": ""
}